LICENSE
README.md
setup.cfg
setup.py
pymodulation/__init__.py
pymodulation/ax100.py
pymodulation/bit_buffer.py
pymodulation/bit_decoder.py
pymodulation/byte_buffer.py
pymodulation/gfsk.py
pymodulation/gmsk.py
pymodulation/golay24.py
pymodulation/pymodulation.py
pymodulation/reed_solomon.py
pymodulation/sync_word.py
pymodulation/version.py
pymodulation.egg-info/PKG-INFO
pymodulation.egg-info/SOURCES.txt
pymodulation.egg-info/dependency_links.txt
pymodulation.egg-info/requires.txt
pymodulation.egg-info/top_level.txt
tests/__init__.py
tests/test_gfsk.py
tests/test_gmsk.py