Metadata-Version: 2.4
Name: pymodulation
Version: 0.1.0
Summary: PyModulation library
Home-page: https://github.com/mgm8/pymodulation
Download-URL: https://github.com/mgm8/pymodulation/releases
Author: Gabriel Mariano Marcelino
Author-email: gabriel.mm8@gmail.com
Maintainer: Gabriel Mariano Marcelino
Maintainer-email: gabriel.mm8@gmail.com
License: LGPL-3.0-only
Platform: Linux
Platform: Windows
Platform: Solaris
Platform: Mac OS-X
Platform: Unix
Classifier: Development Status :: 5 - Production/Stable
Classifier: Environment :: Console
Classifier: Intended Audience :: Developers
Classifier: Intended Audience :: Education
Classifier: Intended Audience :: Science/Research
Classifier: Intended Audience :: Telecommunications Industry
Classifier: Natural Language :: English
Classifier: Operating System :: OS Independent
Classifier: Programming Language :: Python :: 3
Classifier: Topic :: Communications :: Ham Radio
Classifier: Topic :: Education
Classifier: Topic :: Scientific/Engineering
Classifier: Topic :: Software Development :: Libraries
Classifier: Topic :: Software Development :: Libraries :: Python Modules
License-File: LICENSE
Requires-Dist: numpy
Requires-Dist: scipy
Dynamic: author
Dynamic: author-email
Dynamic: classifier
Dynamic: description
Dynamic: description-content-type
Dynamic: download-url
Dynamic: home-page
Dynamic: license
Dynamic: license-file
Dynamic: maintainer
Dynamic: maintainer-email
Dynamic: platform
Dynamic: requires-dist
Dynamic: summary
